__init__.py
jupyter_forge.py
jupyter_forge-0.1.0.data/data/src/SearchPanel.js
jupyter_forge-0.1.0.data/data/src/ToolbarExtension.js
jupyter_forge-0.1.0.data/data/src/index.html
jupyter_forge-0.1.0.data/data/src/package.json
template/index.html
template/package.json
template/Extensions/SearchPanel.js
template/Extensions/ToolbarExtension.js
jupyter_forge-0.1.0.dist-info/METADATA
jupyter_forge-0.1.0.dist-info/WHEEL
jupyter_forge-0.1.0.dist-info/top_level.txt
jupyter_forge-0.1.0.dist-info/RECORD
