Metadata-Version: 2.1
Name: jupyter_forge
Version: 0.1.0
Summary: A tool for extracting data from Revit ACC
Home-page: https://github.com/chuongmep/revit-meows
Author: chuongmep
Author-email: chuongpqvn@gmail.com
Classifier: Programming Language :: Python :: 3
Classifier: License :: OSI Approved :: Apache Software License
Classifier: Operating System :: OS Independent
Requires-Python: >=3.9
Requires-Dist: aps-toolkit
Requires-Dist: requests
Requires-Dist: numpy
Requires-Dist: pandas
